baidubce/__init__.py
baidubce/bce_base_client.py
baidubce/bce_client_configuration.py
baidubce/bce_response.py
baidubce/compat.py
baidubce/exception.py
baidubce/protocol.py
baidubce/region.py
baidubce/utils.py
baidubce/auth/__init__.py
baidubce/auth/bce_credentials.py
baidubce/auth/bce_v1_signer.py
baidubce/http/__init__.py
baidubce/http/bce_http_client.py
baidubce/http/handler.py
baidubce/http/http_content_types.py
baidubce/http/http_headers.py
baidubce/http/http_methods.py
baidubce/retry/__init__.py
baidubce/retry/retry_policy.py
baidubce/services/__init__.py
baidubce/services/bcc/__init__.py
baidubce/services/bcc/bcc_client.py
baidubce/services/bcc/bcc_model.py
baidubce/services/bcc/fpga_card_type.py
baidubce/services/bcc/gpu_card_type.py
baidubce/services/blb/__init__.py
baidubce/services/blb/app_blb_client.py
baidubce/services/blb/blb_client.py
baidubce/services/bmr/__init__.py
baidubce/services/bmr/bmr_client.py
baidubce/services/bos/__init__.py
baidubce/services/bos/bos_client.py
baidubce/services/bos/bos_handler.py
baidubce/services/bos/canned_acl.py
baidubce/services/bos/storage_class.py
baidubce/services/cdn/__init__.py
baidubce/services/cdn/cdn_client.py
baidubce/services/cdn/cdn_stats_param.py
baidubce/services/cfc/__init__.py
baidubce/services/cfc/cfc_client.py
baidubce/services/cfc/cfc_handler.py
baidubce/services/cfc/models.py
baidubce/services/dumap/__init__.py
baidubce/services/dumap/dumap_client.py
baidubce/services/eip/__init__.py
baidubce/services/eip/eip_client.py
baidubce/services/eip/eip_group_client.py
baidubce/services/eip/eip_group_model.py
baidubce/services/eip/model.py
baidubce/services/infinite/__init__.py
baidubce/services/infinite/infinite_client.py
baidubce/services/media/__init__.py
baidubce/services/media/media_client.py
baidubce/services/mvs/__init__.py
baidubce/services/mvs/mvs_client.py
baidubce/services/route/__init__.py
baidubce/services/route/route_client.py
baidubce/services/sms/__init__.py
bce_python_sdk_reborn-0.8.32.dist-info/LICENSE
bce_python_sdk_reborn-0.8.32.dist-info/METADATA
bce_python_sdk_reborn-0.8.32.dist-info/WHEEL
bce_python_sdk_reborn-0.8.32.dist-info/top_level.txt
bce_python_sdk_reborn-0.8.32.dist-info/RECORD
