Metadata-Version: 2.1
Name: bce-python-sdk-reborn
Version: 0.8.32
Summary: BCE SDK for python
Home-page: http://bce.baidu.com
Author: 
Author-email: 
License: Apache License 2.0
Platform: UNKNOWN
Requires-Python: >=2.7, !=3.0.*, !=3.1.*, !=3.2.*, <4
Requires-Dist: future (>=0.6.0)
Requires-Dist: pycryptodome (>=3.9.8)
Requires-Dist: six (>=1.4.0)
